powerdns_cli/__init__.py
powerdns_cli/powerdns_cli.py
powerdns_cli/commands/__init__.py
powerdns_cli/commands/autoprimary.py
powerdns_cli/commands/config.py
powerdns_cli/commands/cryptokey.py
powerdns_cli/commands/metadata.py
powerdns_cli/commands/network.py
powerdns_cli/commands/record.py
powerdns_cli/commands/tsigkey.py
powerdns_cli/commands/view.py
powerdns_cli/commands/zone.py
powerdns_cli/utils/__init__.py
powerdns_cli/utils/logger.py
powerdns_cli/utils/main.py
powerdns_cli/utils/validation.py
powerdns_cli-1.2.1.dist-info/licenses/LICENSE
tests/test_autoprimary.py
tests/test_config.py
tests/test_cryptokey.py
tests/test_metadata.py
tests/test_network.py
tests/test_record.py
tests/test_tsigkey.py
tests/test_utils_logging.py
tests/test_utils_main.py
tests/test_utils_validation.py
tests/test_view.py
tests/test_zone.py
tests/powerdns_cli_test_utils/__init__.py
tests/powerdns_cli_test_utils/testutils.py
powerdns_cli-1.2.1.dist-info/METADATA
powerdns_cli-1.2.1.dist-info/WHEEL
powerdns_cli-1.2.1.dist-info/entry_points.txt
powerdns_cli-1.2.1.dist-info/top_level.txt
powerdns_cli-1.2.1.dist-info/RECORD
