Metadata-Version: 2.4
Name: powerdns-cli
Version: 1.2.1
Summary: PowerDNS Authoritative API client
Author-email: Raphael Grieger <r.grieger@hotmail.com>
License-Expression: GPL-3.0-or-later
Project-URL: Homepage, https://github.com/IamLunchbox/powerdns-cli
Project-URL: Issues, https://github.com/IamLunchbox/powerdns-cli/issues
Classifier: Programming Language :: Python :: 3
Requires-Python: >=3.10
License-File: LICENSE
Requires-Dist: requests>=2.3.0
Requires-Dist: click>=8.3.0
Requires-Dist: platformdirs>=4.5.0
Requires-Dist: tomli>=2.3.0; python_version < "3.11"
Provides-Extra: dev
Requires-Dist: pre-commit; extra == "dev"
Requires-Dist: pylint; extra == "dev"
Requires-Dist: flake8; extra == "dev"
Requires-Dist: tox; extra == "dev"
Requires-Dist: bandit; extra == "dev"
Requires-Dist: pytest; extra == "dev"
Requires-Dist: pytest-mock; extra == "dev"
Requires-Dist: isort; extra == "dev"
Requires-Dist: black; extra == "dev"
Requires-Dist: coverage; extra == "dev"
Requires-Dist: tomli; extra == "dev"
Dynamic: license-file
